CHANGES.txt
LICENSE
MANIFEST.in
README.md
setup.cfg
setup.py
psvtools/__init__.py
psvtools/__main__.py
psvtools/expand.py
psvtools/psv.py
psvtools/trim.py
psvtools/verify.py
psvtools.egg-info/PKG-INFO
psvtools.egg-info/SOURCES.txt
psvtools.egg-info/dependency_links.txt
psvtools.egg-info/entry_points.txt
psvtools.egg-info/not-zip-safe
psvtools.egg-info/top_level.txt
test/test_expand.py
test/test_integration.py
test/test_trim.py
test/test_verify.py