Metadata-Version: 1.1
Name: psvtools
Version: 0.1.0
Summary: Toos for PSV images
Home-page: https://github.com/kageurufu/psvtrim
Author: UNKNOWN
Author-email: UNKNOWN
License: MIT
Keywords: PSV trim expand
Platform: UNKNOWN
Classifier: Development Status :: 3 - Alpha
Classifier: Intended Audience :: Developers
Classifier: License :: OSI Approved :: BSD License
Classifier: Programming Language :: Python
Classifier: Operating System :: POSIX :: Linux
Classifier: Topic :: System
Classifier: Topic :: System :: Archiving
Classifier: Topic :: Utilities
